design.sv
// Code your design here

module jk_ff(output Q, input J, K, rst, clk);     //defining the ports
  reg Q;                       //Q is the flip-flop's output
  always@(posedge clk, posedge rst)    //triggered by positive edge of clock
    begin
      if(rst) begin
        Q <= 1'b0;
      end else begin
        case({J,K})         //concatenation of J & K for case
          2'b00:  Q <= Q;
          2'b01:  Q <= 1'b0;
          2'b10:  Q <= 1'b1;
          2'b11:  Q <= ~Q;
        endcase
      end
    end
endmodule

testbench.sv
// Code your testbench here
// or browse Examples

module test;
  wire Q;
  reg J, K, rst, clk;
  
  jk_ff M_UUT(Q, J, K, rst, clk);
  
  initial
    begin
      $dumpfile("wave.vcd");
      $dumpvars(0,Q, J, K, rst, clk);
      $monitor($time," rst=%b clk=%b J=%b K=%b  Q=%b ", rst, clk, J, K, Q);
      rst=1'b1;clk=1'b0;
      #97 J=1'b1; K=1'b1; rst=1'b0;
      #102 J=1'b0; K=1'b0;
      #6 J=1'b0; K=1'b1;
      #105 J=1'b0; K=1'b0;
      #180 J=1'b1; K=1'b0;
      #60 J=1'b1; K=1'b1;
      #100 $finish;
    end
  always #100 clk=~clk;
endmodule

wave.vcd
$date
	Thu May  7 08:02:47 2020
$end
$version
	Icarus Verilog
$end
$timescale
	1s
$end
$scope module test $end
$var wire 1 ! Q $end
$upscope $end
$scope module test $end
$var reg 1 " J $end
$upscope $end
$scope module test $end
$var reg 1 # K $end
$upscope $end
$scope module test $end
$var reg 1 $ rst $end
$upscope $end
$scope module test $end
$var reg 1 % clk $end
$upscope $end
$enddefinitions $end
#0
$dumpvars
0%
1$
x#
x"
0!
$end
#97
0$
1#
1"
#100
1!
1%
#199
0#
0"
#200
0%
#205
1#
#300
0!
1%
#310
0#
#400
0%
#490
1"
#500
1!
1%
#550
1#
